torchtrainer/__init__.py
torchtrainer/trainer.py
torchtrainer/callbacks/__init__.py
torchtrainer/callbacks/calculate_accuracy_callback.py
torchtrainer/callbacks/calculate_accuracy_per_class_callback.py
torchtrainer/callbacks/calculate_loss_callback.py
torchtrainer/callbacks/lr_batch_scheduler_callback.py
torchtrainer/callbacks/plot_accuracy_per_class_callback.py
torchtrainer/callbacks/plot_callback.py
torchtrainer/callbacks/save_parameters_callback.py
torchtrainer/callbacks/set_tqdm_bar_description_callback.py
torchtrainer/callbacks/training_callback.py
torchtrainer/utils/__init__.py
torchtrainer/utils/epochs_plotter.py
torchtraineretnai-1.0.3.dist-info/METADATA
torchtraineretnai-1.0.3.dist-info/WHEEL
torchtraineretnai-1.0.3.dist-info/top_level.txt
torchtraineretnai-1.0.3.dist-info/RECORD
